pylibrm_lines/__init__.py
pylibrm_lines/exceptions.py
pylibrm_lines/lib.py
pylibrm_lines/renderer.py
pylibrm_lines/scene_info.py
pylibrm_lines/scene_tree.py
pylibrm_lines/text.py
pylibrm_lines-1.1.7.dist-info/METADATA
pylibrm_lines-1.1.7.dist-info/WHEEL
pylibrm_lines-1.1.7.dist-info/licenses/LICENSE
pylibrm_lines-1.1.7.dist-info/RECORD
