Metadata-Version: 2.4
Name: pylibrm-lines
Version: 1.1.7
Summary: 
License-File: LICENSE
Author: RedTTG
Author-email: red@redttg.com
Requires-Python: >=3.9
Classifier: Programming Language :: Python :: 3
Classifier: Programming Language :: Python :: 3.9
Classifier: Programming Language :: Python :: 3.10
Classifier: Programming Language :: Python :: 3.11
Classifier: Programming Language :: Python :: 3.12
Classifier: Programming Language :: Python :: 3.13
Classifier: Programming Language :: Python :: 3.14
Requires-Dist: pillow (>=11.2.1,<12.0.0)
Requires-Dist: rm-api (>=1.0.3,<2.0.0)
Requires-Dist: rm-lines-sys (==1.3)
